COPYING.txt
MANIFEST.in
README.md
setup.py
healthgraph/__init__.py
healthgraph/authmgr.py
healthgraph/content_type.py
healthgraph/exceptions.py
healthgraph/parser.py
healthgraph/resources.py
healthgraph/sessionmgr.py
healthgraph/settings.py
healthgraph_api.egg-info/PKG-INFO
healthgraph_api.egg-info/SOURCES.txt
healthgraph_api.egg-info/dependency_links.txt
healthgraph_api.egg-info/requires.txt
healthgraph_api.egg-info/top_level.txt
samples/bottle/requirements.txt
samples/bottle/runkeeper_demo.conf
samples/bottle/runkeeper_demo.py
samples/bottle/runkeeper_demo.pyc
samples/bottle/views/access_token.html
samples/bottle/views/index.html
samples/bottle/views/welcome.html