Metadata-Version: 1.1
Name: healthgraph-api
Version: 0.3.0
Summary: Python Client for HealthGraph API from RunKeeper.com.
Home-page: http://aouyar.github.com/healthgraph-api
Author: Ali Onur Uyar
Author-email: aouyar at gmail.com
License: GPL
Keywords: Health,Graph,API,RunKeeper
Platform: UNKNOWN
Classifier: Topic :: Internet :: WWW/HTTP
Classifier: Topic :: Software Development :: Libraries :: Python Modules
Classifier: Intended Audience :: Developers
Classifier: License :: OSI Approved :: GNU General Public License (GPL)
Classifier: Programming Language :: Python
Classifier: Development Status :: 3 - Alpha
Classifier: Operating System :: OS Independent
